openselery/__init__.py
openselery/coinbase_connector.py
openselery/collection_utils.py
openselery/commandline.py
openselery/configuration.py
openselery/git_utils.py
openselery/github_connector.py
openselery/librariesio_connector.py
openselery/openselery.py
openselery/os_utils.py
openselery/selery_utils.py
openselery/visualization.py
openselery-0.0.1.dev217.data/data/openselery/ruby_extensions/scan.rb
openselery-0.0.1.dev217.data/scripts/selery
openselery-0.0.1.dev217.dist-info/LICENSE
openselery-0.0.1.dev217.dist-info/METADATA
openselery-0.0.1.dev217.dist-info/WHEEL
openselery-0.0.1.dev217.dist-info/dependency_links.txt
openselery-0.0.1.dev217.dist-info/top_level.txt
openselery-0.0.1.dev217.dist-info/RECORD
